ExasolDatabaseConnector/__init__.py
ExasolDatabaseConnector/ExaDatabaseAbstract/__init__.py
ExasolDatabaseConnector/ExaOdbcDriver/FindDriver.py
ExasolDatabaseConnector/ExaOdbcDriver/__init__.py
ExasolDatabaseConnector/ExaWebSockets/__init__.py
ExasolDatabaseConnector-0.1.7.dist-info/LICENSE
ExasolDatabaseConnector-0.1.7.dist-info/METADATA
ExasolDatabaseConnector-0.1.7.dist-info/WHEEL
ExasolDatabaseConnector-0.1.7.dist-info/top_level.txt
ExasolDatabaseConnector-0.1.7.dist-info/RECORD
