Metadata-Version: 1.2
Name: ExasolDatabaseConnector
Version: 0.1.7
Summary: Exasol database connector class written in python
Home-page: https://github.com/florian-reck/ExaDatabase
Maintainer: Florian Reck
Maintainer-email: support@exasol.com
License: MIT
Platform: UNKNOWN
